nucliadb_telemetry/__init__.py
nucliadb_telemetry/batch_span.py
nucliadb_telemetry/common.py
nucliadb_telemetry/context.py
nucliadb_telemetry/errors.py
nucliadb_telemetry/grpc.py
nucliadb_telemetry/grpc_metrics.py
nucliadb_telemetry/grpc_sentry.py
nucliadb_telemetry/jaeger.py
nucliadb_telemetry/jetstream.py
nucliadb_telemetry/logs.py
nucliadb_telemetry/metrics.py
nucliadb_telemetry/py.typed
nucliadb_telemetry/settings.py
nucliadb_telemetry/tracerprovider.py
nucliadb_telemetry/utils.py
nucliadb_telemetry/fastapi/__init__.py
nucliadb_telemetry/fastapi/context.py
nucliadb_telemetry/fastapi/metrics.py
nucliadb_telemetry/fastapi/tracing.py
nucliadb_telemetry/fastapi/utils.py
nucliadb_telemetry/tests/__init__.py
nucliadb_telemetry/tests/telemetry.py
nucliadb_telemetry/tests/grpc/__init__.py
nucliadb_telemetry/tests/grpc/hellostreamingworld_pb2.py
nucliadb_telemetry/tests/grpc/hellostreamingworld_pb2.pyi
nucliadb_telemetry/tests/grpc/hellostreamingworld_pb2_grpc.py
nucliadb_telemetry/tests/grpc/hellostreamingworld_pb2_grpc.pyi
nucliadb_telemetry/tests/grpc/helloworld_pb2.py
nucliadb_telemetry/tests/grpc/helloworld_pb2.pyi
nucliadb_telemetry/tests/grpc/helloworld_pb2_grpc.py
nucliadb_telemetry/tests/grpc/helloworld_pb2_grpc.pyi
nucliadb_telemetry-6.11.1.post5854.dist-info/METADATA
nucliadb_telemetry-6.11.1.post5854.dist-info/WHEEL
nucliadb_telemetry-6.11.1.post5854.dist-info/top_level.txt
nucliadb_telemetry-6.11.1.post5854.dist-info/RECORD
