Metadata-Version: 2.4
Name: nucliadb_telemetry
Version: 6.11.1.post5854
Summary: NucliaDB Telemetry Library Python process
Author-email: Nuclia <nucliadb@nuclia.com>
License-Expression: AGPL-3.0-or-later
Project-URL: Homepage, https://nuclia.com
Project-URL: Repository, https://github.com/nuclia/nucliadb
Classifier: Development Status :: 3 - Alpha
Classifier: Intended Audience :: Developers
Classifier: Intended Audience :: Information Technology
Classifier: Framework :: AsyncIO
Classifier: Programming Language :: Python
Classifier: Programming Language :: Python :: 3.10
Classifier: Programming Language :: Python :: 3.11
Classifier: Programming Language :: Python :: 3.12
Classifier: Programming Language :: Python :: 3 :: Only
Classifier: Topic :: System :: Monitoring
Requires-Python: <4,>=3.10
Requires-Dist: pydantic>=2.6
Requires-Dist: pydantic-settings>=2.2
Requires-Dist: prometheus-client>=0.12.0
Requires-Dist: orjson>=3.6.7
Requires-Dist: wrapt>=1.14.1
Provides-Extra: otel
Requires-Dist: opentelemetry-sdk>=1.21.0; extra == "otel"
Requires-Dist: opentelemetry-api>=1.21.0; extra == "otel"
Requires-Dist: opentelemetry-proto>=1.21.0; extra == "otel"
Requires-Dist: opentelemetry-exporter-jaeger-thrift>=1.21.0; extra == "otel"
Requires-Dist: opentelemetry-propagator-b3>=1.21.0; extra == "otel"
Requires-Dist: opentelemetry-instrumentation-fastapi>=0.42b0; extra == "otel"
Requires-Dist: opentelemetry-instrumentation-aiohttp-client>=0.42b0; extra == "otel"
Requires-Dist: opentelemetry-instrumentation-httpx>=0.42b0; extra == "otel"
Requires-Dist: opentelemetry-semantic-conventions>=0.42b0; extra == "otel"
Provides-Extra: grpc
Requires-Dist: grpcio>=1.71.0; extra == "grpc"
Requires-Dist: grpcio-health-checking>=1.71.0; extra == "grpc"
Requires-Dist: grpcio-channelz>=1.71.0; extra == "grpc"
Requires-Dist: grpcio-status>=1.71.0; extra == "grpc"
Requires-Dist: grpcio-tools>=1.71.0; extra == "grpc"
Requires-Dist: grpcio-testing>=1.71.0; extra == "grpc"
Requires-Dist: grpcio-reflection>=1.71.0; extra == "grpc"
Requires-Dist: opentelemetry-sdk>=1.21.0; extra == "grpc"
Requires-Dist: opentelemetry-api>=1.21.0; extra == "grpc"
Requires-Dist: opentelemetry-proto>=1.21.0; extra == "grpc"
Requires-Dist: opentelemetry-exporter-jaeger-thrift>=1.21.0; extra == "grpc"
Requires-Dist: opentelemetry-propagator-b3>=1.21.0; extra == "grpc"
Requires-Dist: opentelemetry-instrumentation-fastapi>=0.42b0; extra == "grpc"
Requires-Dist: opentelemetry-instrumentation-aiohttp-client>=0.42b0; extra == "grpc"
Requires-Dist: opentelemetry-instrumentation-httpx>=0.42b0; extra == "grpc"
Requires-Dist: opentelemetry-semantic-conventions>=0.42b0; extra == "grpc"
Provides-Extra: nats
Requires-Dist: nats-py[nkeys]>=2.5.0; extra == "nats"
Requires-Dist: PyNaCl; extra == "nats"
Requires-Dist: opentelemetry-sdk>=1.21.0; extra == "nats"
Requires-Dist: opentelemetry-api>=1.21.0; extra == "nats"
Requires-Dist: opentelemetry-proto>=1.21.0; extra == "nats"
Requires-Dist: opentelemetry-exporter-jaeger-thrift>=1.21.0; extra == "nats"
Requires-Dist: opentelemetry-propagator-b3>=1.21.0; extra == "nats"
Requires-Dist: opentelemetry-instrumentation-fastapi>=0.42b0; extra == "nats"
Requires-Dist: opentelemetry-instrumentation-aiohttp-client>=0.42b0; extra == "nats"
Requires-Dist: opentelemetry-instrumentation-httpx>=0.42b0; extra == "nats"
Requires-Dist: opentelemetry-semantic-conventions>=0.42b0; extra == "nats"
Provides-Extra: fastapi
Requires-Dist: fastapi; extra == "fastapi"
Requires-Dist: opentelemetry-sdk>=1.21.0; extra == "fastapi"
Requires-Dist: opentelemetry-api>=1.21.0; extra == "fastapi"
Requires-Dist: opentelemetry-proto>=1.21.0; extra == "fastapi"
Requires-Dist: opentelemetry-exporter-jaeger-thrift>=1.21.0; extra == "fastapi"
Requires-Dist: opentelemetry-propagator-b3>=1.21.0; extra == "fastapi"
Requires-Dist: opentelemetry-instrumentation-fastapi>=0.42b0; extra == "fastapi"
Requires-Dist: opentelemetry-instrumentation-aiohttp-client>=0.42b0; extra == "fastapi"
Requires-Dist: opentelemetry-instrumentation-httpx>=0.42b0; extra == "fastapi"
Requires-Dist: opentelemetry-semantic-conventions>=0.42b0; extra == "fastapi"
Provides-Extra: all
Requires-Dist: opentelemetry-sdk>=1.21.0; extra == "all"
Requires-Dist: opentelemetry-api>=1.21.0; extra == "all"
Requires-Dist: opentelemetry-proto>=1.21.0; extra == "all"
Requires-Dist: opentelemetry-exporter-jaeger-thrift>=1.21.0; extra == "all"
Requires-Dist: opentelemetry-propagator-b3>=1.21.0; extra == "all"
Requires-Dist: opentelemetry-instrumentation-fastapi>=0.42b0; extra == "all"
Requires-Dist: opentelemetry-instrumentation-aiohttp-client>=0.42b0; extra == "all"
Requires-Dist: opentelemetry-instrumentation-httpx>=0.42b0; extra == "all"
Requires-Dist: opentelemetry-semantic-conventions>=0.42b0; extra == "all"
Requires-Dist: grpcio>=1.71.0; extra == "all"
Requires-Dist: grpcio-health-checking>=1.71.0; extra == "all"
Requires-Dist: grpcio-channelz>=1.71.0; extra == "all"
Requires-Dist: grpcio-status>=1.71.0; extra == "all"
Requires-Dist: grpcio-tools>=1.71.0; extra == "all"
Requires-Dist: grpcio-testing>=1.71.0; extra == "all"
Requires-Dist: grpcio-reflection>=1.71.0; extra == "all"
Requires-Dist: nats-py[nkeys]>=2.5.0; extra == "all"
Requires-Dist: PyNaCl; extra == "all"
Requires-Dist: fastapi; extra == "all"
